        <Macro name="MASM32Template" Ctrl="no" Alt="no" Shift="no" Key="0">
            <Action type="1" message="2170" wParam="0" lParam="0" sParam="." />
            <Action type="1" message="2170" wParam="0" lParam="0" sParam="3" />
            <Action type="1" message="2170" wParam="0" lParam="0" sParam="8" />
            <Action type="1" message="2170" wParam="0" lParam="0" sParam="6" />
            <Action type="1" message="2170" wParam="0" lParam="0" sParam="&#x000D;" />
            <Action type="1" message="2170" wParam="0" lParam="0" sParam="&#x000A;" />
            <Action type="1" message="2170" wParam="0" lParam="0" sParam="." />
            <Action type="1" message="2170" wParam="0" lParam="0" sParam="m" />
            <Action type="1" message="2170" wParam="0" lParam="0" sParam="o" />
            <Action type="1" message="2170" wParam="0" lParam="0" sParam="d" />
            <Action type="1" message="2170" wParam="0" lParam="0" sParam="e" />
            <Action type="1" message="2170" wParam="0" lParam="0" sParam="l" />
            <Action type="1" message="2170" wParam="0" lParam="0" sParam=" " />
            <Action type="1" message="2170" wParam="0" lParam="0" sParam="f" />
            <Action type="1" message="2170" wParam="0" lParam="0" sParam="l" />
            <Action type="1" message="2170" wParam="0" lParam="0" sParam="a" />
            <Action type="1" message="2170" wParam="0" lParam="0" sParam="t" />
            <Action type="1" message="2170" wParam="0" lParam="0" sParam="," />
            <Action type="1" message="2170" wParam="0" lParam="0" sParam=" " />
            <Action type="1" message="2170" wParam="0" lParam="0" sParam="s" />
            <Action type="1" message="2170" wParam="0" lParam="0" sParam="t" />
            <Action type="1" message="2170" wParam="0" lParam="0" sParam="d" />
            <Action type="1" message="2170" wParam="0" lParam="0" sParam="c" />
            <Action type="1" message="2170" wParam="0" lParam="0" sParam="a" />
            <Action type="1" message="2170" wParam="0" lParam="0" sParam="l" />
            <Action type="1" message="2170" wParam="0" lParam="0" sParam="l" />
            <Action type="1" message="2170" wParam="0" lParam="0" sParam="&#x000D;" />
            <Action type="1" message="2170" wParam="0" lParam="0" sParam="&#x000A;" />
            <Action type="1" message="2170" wParam="0" lParam="0" sParam="o" />
            <Action type="1" message="2170" wParam="0" lParam="0" sParam="p" />
            <Action type="1" message="2170" wParam="0" lParam="0" sParam="t" />
            <Action type="1" message="2170" wParam="0" lParam="0" sParam="i" />
            <Action type="1" message="2170" wParam="0" lParam="0" sParam="o" />
            <Action type="1" message="2170" wParam="0" lParam="0" sParam="n" />
            <Action type="1" message="2170" wParam="0" lParam="0" sParam=" " />
            <Action type="1" message="2170" wParam="0" lParam="0" sParam="c" />
            <Action type="1" message="2170" wParam="0" lParam="0" sParam="a" />
            <Action type="1" message="2170" wParam="0" lParam="0" sParam="s" />
            <Action type="1" message="2170" wParam="0" lParam="0" sParam="e" />
            <Action type="1" message="2170" wParam="0" lParam="0" sParam="m" />
            <Action type="1" message="2170" wParam="0" lParam="0" sParam="a" />
            <Action type="1" message="2170" wParam="0" lParam="0" sParam="p" />
            <Action type="1" message="2170" wParam="0" lParam="0" sParam="." />
            <Action type="1" message="2170" wParam="0" lParam="0" sParam="n" />
            <Action type="1" message="2170" wParam="0" lParam="0" sParam="o" />
            <Action type="1" message="2170" wParam="0" lParam="0" sParam="n" />
            <Action type="1" message="2170" wParam="0" lParam="0" sParam="e" />
            <Action type="0" message="2304" wParam="0" lParam="0" sParam="" />
            <Action type="0" message="2304" wParam="0" lParam="0" sParam="" />
            <Action type="0" message="2304" wParam="0" lParam="0" sParam="" />
            <Action type="0" message="2304" wParam="0" lParam="0" sParam="" />
            <Action type="0" message="2304" wParam="0" lParam="0" sParam="" />
            <Action type="0" message="2180" wParam="0" lParam="0" sParam="" />
            <Action type="1" message="2170" wParam="0" lParam="0" sParam=":" />
            <Action type="0" message="2451" wParam="0" lParam="0" sParam="" />
            <Action type="1" message="2170" wParam="0" lParam="0" sParam="&#x000D;" />
            <Action type="1" message="2170" wParam="0" lParam="0" sParam="&#x000A;" />
            <Action type="1" message="2170" wParam="0" lParam="0" sParam="&#x000D;" />
            <Action type="1" message="2170" wParam="0" lParam="0" sParam="&#x000A;" />
            <Action type="1" message="2170" wParam="0" lParam="0" sParam="i" />
            <Action type="1" message="2170" wParam="0" lParam="0" sParam="n" />
            <Action type="1" message="2170" wParam="0" lParam="0" sParam="c" />
            <Action type="1" message="2170" wParam="0" lParam="0" sParam="l" />
            <Action type="1" message="2170" wParam="0" lParam="0" sParam="u" />
            <Action type="1" message="2170" wParam="0" lParam="0" sParam="d" />
            <Action type="1" message="2170" wParam="0" lParam="0" sParam="e" />
            <Action type="1" message="2170" wParam="0" lParam="0" sParam=" " />
            <Action type="1" message="2170" wParam="0" lParam="0" sParam="k" />
            <Action type="1" message="2170" wParam="0" lParam="0" sParam="e" />
            <Action type="1" message="2170" wParam="0" lParam="0" sParam="r" />
            <Action type="1" message="2170" wParam="0" lParam="0" sParam="n" />
            <Action type="1" message="2170" wParam="0" lParam="0" sParam="e" />
            <Action type="1" message="2170" wParam="0" lParam="0" sParam="l" />
            <Action type="1" message="2170" wParam="0" lParam="0" sParam="3" />
            <Action type="1" message="2170" wParam="0" lParam="0" sParam="2" />
            <Action type="1" message="2170" wParam="0" lParam="0" sParam="." />
            <Action type="1" message="2170" wParam="0" lParam="0" sParam="l" />
            <Action type="1" message="2170" wParam="0" lParam="0" sParam="i" />
            <Action type="1" message="2170" wParam="0" lParam="0" sParam="b" />
            <Action type="1" message="2170" wParam="0" lParam="0" sParam="&#x000D;" />
            <Action type="1" message="2170" wParam="0" lParam="0" sParam="&#x000A;" />
            <Action type="0" message="2326" wParam="0" lParam="0" sParam="" />
            <Action type="0" message="2326" wParam="0" lParam="0" sParam="" />
            <Action type="0" message="2326" wParam="0" lParam="0" sParam="" />
            <Action type="0" message="2326" wParam="0" lParam="0" sParam="" />
            <Action type="1" message="2170" wParam="0" lParam="0" sParam="i" />
            <Action type="1" message="2170" wParam="0" lParam="0" sParam="n" />
            <Action type="1" message="2170" wParam="0" lParam="0" sParam="c" />
            <Action type="1" message="2170" wParam="0" lParam="0" sParam="&#x000D;" />
            <Action type="1" message="2170" wParam="0" lParam="0" sParam="&#x000A;" />
            <Action type="1" message="2170" wParam="0" lParam="0" sParam="i" />
            <Action type="1" message="2170" wParam="0" lParam="0" sParam="n" />
            <Action type="1" message="2170" wParam="0" lParam="0" sParam="c" />
            <Action type="1" message="2170" wParam="0" lParam="0" sParam="l" />
            <Action type="1" message="2170" wParam="0" lParam="0" sParam="u" />
            <Action type="1" message="2170" wParam="0" lParam="0" sParam="d" />
            <Action type="1" message="2170" wParam="0" lParam="0" sParam="e" />
            <Action type="1" message="2170" wParam="0" lParam="0" sParam="l" />
            <Action type="1" message="2170" wParam="0" lParam="0" sParam="i" />
            <Action type="1" message="2170" wParam="0" lParam="0" sParam="b" />
            <Action type="1" message="2170" wParam="0" lParam="0" sParam=" " />
            <Action type="1" message="2170" wParam="0" lParam="0" sParam="k" />
            <Action type="1" message="2170" wParam="0" lParam="0" sParam="e" />
            <Action type="1" message="2170" wParam="0" lParam="0" sParam="r" />
            <Action type="1" message="2170" wParam="0" lParam="0" sParam="n" />
            <Action type="1" message="2170" wParam="0" lParam="0" sParam="e" />
            <Action type="1" message="2170" wParam="0" lParam="0" sParam="l" />
            <Action type="1" message="2170" wParam="0" lParam="0" sParam="3" />
            <Action type="1" message="2170" wParam="0" lParam="0" sParam="2" />
            <Action type="1" message="2170" wParam="0" lParam="0" sParam="." />
            <Action type="1" message="2170" wParam="0" lParam="0" sParam="l" />
            <Action type="1" message="2170" wParam="0" lParam="0" sParam="i" />
            <Action type="1" message="2170" wParam="0" lParam="0" sParam="b" />
            <Action type="1" message="2170" wParam="0" lParam="0" sParam="&#x000D;" />
            <Action type="1" message="2170" wParam="0" lParam="0" sParam="&#x000A;" />
            <Action type="1" message="2170" wParam="0" lParam="0" sParam="&#x000D;" />
            <Action type="1" message="2170" wParam="0" lParam="0" sParam="&#x000A;" />
            <Action type="1" message="2170" wParam="0" lParam="0" sParam="." />
            <Action type="1" message="2170" wParam="0" lParam="0" sParam="d" />
            <Action type="1" message="2170" wParam="0" lParam="0" sParam="a" />
            <Action type="1" message="2170" wParam="0" lParam="0" sParam="t" />
            <Action type="1" message="2170" wParam="0" lParam="0" sParam="a" />
            <Action type="1" message="2170" wParam="0" lParam="0" sParam="&#x000D;" />
            <Action type="1" message="2170" wParam="0" lParam="0" sParam="&#x000A;" />
            <Action type="1" message="2170" wParam="0" lParam="0" sParam="&#x000D;" />
            <Action type="1" message="2170" wParam="0" lParam="0" sParam="&#x000A;" />
            <Action type="1" message="2170" wParam="0" lParam="0" sParam="." />
            <Action type="1" message="2170" wParam="0" lParam="0" sParam="c" />
            <Action type="1" message="2170" wParam="0" lParam="0" sParam="o" />
            <Action type="1" message="2170" wParam="0" lParam="0" sParam="d" />
            <Action type="1" message="2170" wParam="0" lParam="0" sParam="e" />
            <Action type="1" message="2170" wParam="0" lParam="0" sParam="&#x000D;" />
            <Action type="1" message="2170" wParam="0" lParam="0" sParam="&#x000A;" />
            <Action type="1" message="2170" wParam="0" lParam="0" sParam="_" />
            <Action type="1" message="2170" wParam="0" lParam="0" sParam="m" />
            <Action type="1" message="2170" wParam="0" lParam="0" sParam="a" />
            <Action type="1" message="2170" wParam="0" lParam="0" sParam="i" />
            <Action type="1" message="2170" wParam="0" lParam="0" sParam="n" />
            <Action type="1" message="2170" wParam="0" lParam="0" sParam="&#x000D;" />
            <Action type="1" message="2170" wParam="0" lParam="0" sParam="&#x000A;" />
            <Action type="0" message="2327" wParam="0" lParam="0" sParam="" />
            <Action type="1" message="2170" wParam="0" lParam="0" sParam="i" />
            <Action type="1" message="2170" wParam="0" lParam="0" sParam="n" />
            <Action type="1" message="2170" wParam="0" lParam="0" sParam="v" />
            <Action type="1" message="2170" wParam="0" lParam="0" sParam="o" />
            <Action type="1" message="2170" wParam="0" lParam="0" sParam="k" />
            <Action type="1" message="2170" wParam="0" lParam="0" sParam="e" />
            <Action type="1" message="2170" wParam="0" lParam="0" sParam=" " />
            <Action type="1" message="2170" wParam="0" lParam="0" sParam="E" />
            <Action type="1" message="2170" wParam="0" lParam="0" sParam="x" />
            <Action type="1" message="2170" wParam="0" lParam="0" sParam="i" />
            <Action type="1" message="2170" wParam="0" lParam="0" sParam="t" />
            <Action type="1" message="2170" wParam="0" lParam="0" sParam="P" />
            <Action type="1" message="2170" wParam="0" lParam="0" sParam="r" />
            <Action type="1" message="2170" wParam="0" lParam="0" sParam="o" />
            <Action type="1" message="2170" wParam="0" lParam="0" sParam="c" />
            <Action type="1" message="2170" wParam="0" lParam="0" sParam="e" />
            <Action type="1" message="2170" wParam="0" lParam="0" sParam="s" />
            <Action type="1" message="2170" wParam="0" lParam="0" sParam="s" />
            <Action type="1" message="2170" wParam="0" lParam="0" sParam="," />
            <Action type="1" message="2170" wParam="0" lParam="0" sParam=" " />
            <Action type="1" message="2170" wParam="0" lParam="0" sParam="0" />
            <Action type="0" message="2304" wParam="0" lParam="0" sParam="" />
            <Action type="0" message="2304" wParam="0" lParam="0" sParam="" />
            <Action type="0" message="2304" wParam="0" lParam="0" sParam="" />
            <Action type="0" message="2304" wParam="0" lParam="0" sParam="" />
            <Action type="0" message="2304" wParam="0" lParam="0" sParam="" />
            <Action type="0" message="2304" wParam="0" lParam="0" sParam="" />
            <Action type="0" message="2304" wParam="0" lParam="0" sParam="" />
            <Action type="0" message="2304" wParam="0" lParam="0" sParam="" />
            <Action type="0" message="2304" wParam="0" lParam="0" sParam="" />
            <Action type="0" message="2304" wParam="0" lParam="0" sParam="" />
            <Action type="0" message="2304" wParam="0" lParam="0" sParam="" />
            <Action type="0" message="2304" wParam="0" lParam="0" sParam="" />
            <Action type="0" message="2304" wParam="0" lParam="0" sParam="" />
            <Action type="0" message="2304" wParam="0" lParam="0" sParam="" />
            <Action type="0" message="2304" wParam="0" lParam="0" sParam="" />
            <Action type="0" message="2304" wParam="0" lParam="0" sParam="" />
            <Action type="0" message="2304" wParam="0" lParam="0" sParam="" />
            <Action type="0" message="2304" wParam="0" lParam="0" sParam="" />
            <Action type="0" message="2304" wParam="0" lParam="0" sParam="" />
            <Action type="0" message="2304" wParam="0" lParam="0" sParam="" />
            <Action type="0" message="2304" wParam="0" lParam="0" sParam="" />
            <Action type="1" message="2170" wParam="0" lParam="0" sParam="&#x000D;" />
            <Action type="1" message="2170" wParam="0" lParam="0" sParam="&#x000A;" />
            <Action type="0" message="2327" wParam="0" lParam="0" sParam="" />
            <Action type="0" message="2451" wParam="0" lParam="0" sParam="" />
            <Action type="0" message="2302" wParam="0" lParam="0" sParam="" />
            <Action type="0" message="2300" wParam="0" lParam="0" sParam="" />
            <Action type="0" message="2300" wParam="0" lParam="0" sParam="" />
            <Action type="1" message="2170" wParam="0" lParam="0" sParam="&#x000D;" />
            <Action type="1" message="2170" wParam="0" lParam="0" sParam="&#x000A;" />
            <Action type="1" message="2170" wParam="0" lParam="0" sParam="e" />
            <Action type="1" message="2170" wParam="0" lParam="0" sParam="n" />
            <Action type="1" message="2170" wParam="0" lParam="0" sParam="d" />
            <Action type="0" message="2327" wParam="0" lParam="0" sParam="" />
            <Action type="1" message="2170" wParam="0" lParam="0" sParam="_" />
            <Action type="1" message="2170" wParam="0" lParam="0" sParam="m" />
            <Action type="1" message="2170" wParam="0" lParam="0" sParam="a" />
            <Action type="1" message="2170" wParam="0" lParam="0" sParam="i" />
            <Action type="1" message="2170" wParam="0" lParam="0" sParam="n" />
        </Macro>